ut_http/__init__.py
ut_http/__version__.py
ut_http/aiohttp_.py
ut_http/http_.py
ut_http/httpx_.py
ut_http/py.typed
ut_http/requests_.py
ut_http/uri.py
ut_http/urllib3_.py
ut_http/utils.py
ut_http-1.0.0.20250909.dist-info/licenses/LICENSE.txt
ut_http-1.0.0.20250909.dist-info/METADATA
ut_http-1.0.0.20250909.dist-info/WHEEL
ut_http-1.0.0.20250909.dist-info/top_level.txt
ut_http-1.0.0.20250909.dist-info/RECORD
