Metadata-Version: 2.4
Name: ut_http
Version: 1.0.0.20250909
Summary: Utilities for Dictionaries
Author-email: Bernd Stroehle <bernd.stroehle@gmail.com>
Maintainer-email: Bernd Stroehle <bernd.stroehle@gmail.com>
License-Expression: GPL-3.0-only WITH Classpath-exception-2.0 OR BSD-3-Clause
Project-URL: Source Code, https://github.com/bs29/ut_http/tree/master
Project-URL: Homepage, https://kosakya.de/
Project-URL: Documentation, https://ut-dic.readthedocs.io/en/latest
Classifier: Development Status :: 5 - Production/Stable
Classifier: Intended Audience :: Developers
Classifier: Operating System :: OS Independent
Classifier: Programming Language :: Python :: 3.12
Classifier: Natural Language :: English
Classifier: Topic :: Software Development :: Libraries :: Python Modules
Requires-Python: >=3.10
License-File: LICENSE.txt
Requires-Dist: aiohttp>=3.12.14
Requires-Dist: httpx>=0.28.1
Requires-Dist: Requests>=2.32.5
Requires-Dist: urllib3>=2.5.0
Requires-Dist: ut_com>=1.2.0.20250827
Requires-Dist: ut_dic>=1.3.5.20250909
Requires-Dist: ut_log>=1.3.0.20250821
Requires-Dist: ut_obj>=1.2.0.20250827
Requires-Dist: xmltodict>=0.14.2
Dynamic: license-file
